pyserilog_settings_configuration/__init__.py
pyserilog_settings_configuration/configuration_extensions.py
pyserilog_settings_configuration/settings/__init__.py
pyserilog_settings_configuration/settings/configuration_argument_value.py
pyserilog_settings_configuration/settings/configuration_reader.py
pyserilog_settings_configuration/settings/configuration_reader_options.py
pyserilog_settings_configuration/settings/iconfiguration_reader.py
pyserilog_settings_configuration/settings/object_argument_value.py
pyserilog_settings_configuration/settings/resolution_context.py
pyserilog_settings_configuration/settings/setting_configuration_extensions.py
pyserilog_settings_configuration/settings/string_argument_value.py
pyserilog_settings_configuration/settings/utils.py
pyserilog_settings_configuration-0.3.0.dist-info/LICENSE
pyserilog_settings_configuration-0.3.0.dist-info/METADATA
pyserilog_settings_configuration-0.3.0.dist-info/WHEEL
pyserilog_settings_configuration-0.3.0.dist-info/top_level.txt
pyserilog_settings_configuration-0.3.0.dist-info/RECORD
