Metadata-Version: 2.1
Name: pyserilog-settings-configuration
Version: 0.3.0
Summary: pyton version of serilog a structured logging library
Author: Reza Sadeghi
Author-email: rezasadeghikhas@gmail.com
License: Apache2
Classifier: Development Status :: 3 - Alpha
Classifier: Intended Audience :: Developers
Classifier: Topic :: System :: Logging
Classifier: Topic :: Software Development :: Libraries
Classifier: Topic :: Internet :: Log Analysis
Classifier: License :: OSI Approved :: Apache Software License
Classifier: Programming Language :: Python :: 3.11
License-File: LICENSE
Requires-Dist: pyconfig-extension >=0.1.0a3
